subproess_dotpro/__init__.py
subproess_dotpro/error.py
subproess_dotpro/run_load.py
subproess_dotpro/setup.py
subproess_dotpro-2.2.0.2.dist-info/LICENSE.txt
subproess_dotpro-2.2.0.2.dist-info/METADATA
subproess_dotpro-2.2.0.2.dist-info/WHEEL
subproess_dotpro-2.2.0.2.dist-info/top_level.txt
subproess_dotpro-2.2.0.2.dist-info/RECORD
