Metadata-Version: 2.1
Name: subproess-dotpro
Version: 2.2.0.2
Summary: dot pro subproess 's pkg
Home-page: http://www.dotcs.community
Author: 梦境中雨
Author-email: 121980156@QQ.com
Classifier: Programming Language :: Python :: 3
Classifier: License :: OSI Approved :: MIT License
Classifier: Operating System :: OS Independent
Requires-Python: >=3.2
License-File: LICENSE.txt
